TerraHarmonize/__init__.py
TerraHarmonize/const.py
TerraHarmonize/TerraHarmonize.py
TerraHarmonize/utils.py
terraharmonize-0.1.4.dist-info/LICENSE
terraharmonize-0.1.4.dist-info/METADATA
terraharmonize-0.1.4.dist-info/WHEEL
terraharmonize-0.1.4.dist-info/RECORD
