Metadata-Version: 2.1
Name: TerraHarmonize
Version: 0.1.4
Summary: A powerful and efficient package designed for the SatSure Sage GIS team, enabling precise and seamless POC matching and D1-D2 matching across all states.
License: GPLv3
Keywords: SatSure,TerraHarmonize,Sage,POC
Author: chandramohan
Author-email: chandramohan@satsure.co
Requires-Python: >=3.9,<3.11
Classifier: License :: Other/Proprietary License
Classifier: Programming Language :: Python :: 3
Classifier: Programming Language :: Python :: 3.9
Classifier: Programming Language :: Python :: 3.10
Requires-Dist: fuzzywuzzy (==0.18.0)
Requires-Dist: numpy (==1.26.0)
Requires-Dist: pandas (==2.1.1)
Project-URL: Documentation, https://terraharmonize-docs.readthedocs.io/en/latest/index.html
